moat/lib/repl/__init__.py
moat/lib/repl/_module_completer.py
moat/lib/repl/_test.py
moat/lib/repl/base_eventqueue.py
moat/lib/repl/commands.py
moat/lib/repl/completing_reader.py
moat/lib/repl/console.py
moat/lib/repl/fancy_termios.py
moat/lib/repl/historical_reader.py
moat/lib/repl/input_.py
moat/lib/repl/keymap.py
moat/lib/repl/pager.py
moat/lib/repl/reader.py
moat/lib/repl/readline.py
moat/lib/repl/rpc.py
moat/lib/repl/simple_interact.py
moat/lib/repl/terminfo.py
moat/lib/repl/trace.py
moat/lib/repl/types.py
moat/lib/repl/unix_console.py
moat/lib/repl/unix_eventqueue.py
moat/lib/repl/utils.py
moat/lib/repl/windows_console.py
moat/lib/repl/windows_eventqueue.py
moat_lib_repl-0.1.2.dist-info/licenses/LICENSE
moat_lib_repl-0.1.2.dist-info/licenses/LICENSE.txt
moat_lib_repl-0.1.2.dist-info/METADATA
moat_lib_repl-0.1.2.dist-info/WHEEL
moat_lib_repl-0.1.2.dist-info/top_level.txt
moat_lib_repl-0.1.2.dist-info/RECORD
