Metadata-Version: 2.4
Name: moat-lib-repl
Version: 0.1.2
Summary: An async readline re-implementation
Maintainer-email: Matthias Urlichs <matthias@urlichs.de>
Project-URL: homepage, https://m-o-a-t.org
Project-URL: repository, https://github.com/M-o-a-T/moat
Keywords: MoaT
Classifier: Development Status :: 4 - Beta
Classifier: Framework :: AnyIO
Classifier: Framework :: Trio
Classifier: Framework :: AsyncIO
Classifier: Programming Language :: Python :: 3
Classifier: Intended Audience :: Developers
Requires-Python: >=3.12
License-File: LICENSE
License-File: LICENSE.txt
Requires-Dist: anyio~=4.0
Requires-Dist: moat-lib-proxy~=0.1.0
Requires-Dist: moat-lib-rpc~=0.5.1
Requires-Dist: moat-lib-stream~=0.1.3
Dynamic: license-file
